{
  "alexandre-sarran": "qiqi-zhu",
  "amelie-fournier": "toyese-oyegoke",
  "annie-tshika": "suzanne-sarran",
  "charlene-picq": "yvettes-campoy",
  "denis-blum": "timothee-sarran",
  "dimitri-cobb": "jung-yeon-gosselin",
  "dwight-bornes": "stephane-hamelin",
  "enora-corlay": "nathalie-merlano",
  "etienne-gerber": "enora-corlay",
  "etienne-sarran": "marie-julien",
  "fabrice-lingois": "linda-hamelin",
  "flora-julien": "laetitia-stauffer",
  "gilles-campoy": "laetitia-grare",
  "helene-bazille": "amelie-fournier",
  "isaque-carreto": "matthieu-sarran",
  "ivan-hamelin": "vallouise-sarran",
  "jean-francois-maniere": "helene-bazille",
  "jeronimo-avelluneda": "etienne-sarran",
  "joshua-sims": "yi-hsuan-chen",
  "jung-yeon-gosselin": "jean-francois-maniere",
  "kalhou-vang": "charlene-picq",
  "karine-comte": "denis-blum",
  "laetitia-grare": "etienne-gerber",
  "laetitia-stauffer": "joshua-sims",
  "linda-hamelin": "thierry-comte",
  "mailys-blum": "teresa-carreto",
  "marie-noelle-gerber": "gilles-campoy",
  "marie-julien": "ivan-hamelin",
  "matthieu-sarran": "flora-julien",
  "mireille-yoyotte-landry": "orlane-batman",
  "nathalie-merlano": "mailys-blum",
  "orlane-batman": "pierrick-fournier",
  "pierrick-fournier": "dwight-bornes",
  "qiqi-zhu": "soohyun-vang",
  "rafaella-bartz-pena": "karine-comte",
  "soohyun-vang": "annie-tshika",
  "stephane-hamelin": "marie-noelle-gerber",
  "suzanne-sarran": "trina-collet",
  "tehele-mpassi": "kalhou-vang",
  "teresa-carreto": "mireille-yoyotte-landry",
  "thierry-comte": "dimitri-cobb",
  "timothee-sarran": "vincent-collet",
  "tom-kristanek": "fabrice-lingois",
  "toyese-oyegoke": "tom-kristanek",
  "trina-collet": "isaque-carreto",
  "vallouise-sarran": "jeronimo-avelluneda",
  "vincent-collet": "rafaella-bartz-pena",
  "yi-hsuan-chen": "tehele-mpassi",
  "yvettes-campoy": "alexandre-sarran"
}
